{
  "productCode": "1070316",
  "productName": "[특가~9/29] 샘키즈 하이가드 데이베드 범퍼가드 4면형 (DIY)",
  "price": 239000,
  "productUrl": "https://store.hanssem.com/goods/1070316",
  "mainImage": "https://image.hanssem.com/hsimg/gds/1050/1070/1070316_A1.jpg?v=20250908095200",
  "category": "키즈룸",
  "detailHTML": "<div class=\"img-box\">\n\t<picture data-origin=\"admin-editor-img\">\n\t\t<source media=\"(max-width:767px)\" srcset=\"https://image.hanssem.com/hsimg/gds/Editor/2024/10/07/1728266384384_0.jpg?w=750 2x, https://image.hanssem.com/hsimg/gds/Editor/2024/10/07/1728266384384_0.jpg?w=1125 3x\">\n\t\t<source media=\"(min-width:768px)\" srcset=\"https://image.hanssem.com/hsimg/gds/Editor/2024/10/07/1728266384384_0.jpg?w=870 1x, https://image.hanssem.com/hsimg/gds/Editor/2024/10/07/1728266384384_0.jpg?w=1740 2x, https://image.hanssem.com/hsimg/gds/Editor/2024/10/07/1728266384384_0.jpg?w=2610 3x\">\n\t\t<img src=\"https://image.hanssem.com/hsimg/gds/Editor/2024/10/07/1728266384384_0.jpg\" width=\"\" height=\"\">\n\t</picture>\n</div>\n<div class=\"cont-txt\"><h2><span style=\"white-space-collapse: preserve;\">샘키즈 침대에 딱 맞는 맞춤형 범퍼가드</span><br></h2><p></p><p><span style=\"white-space-collapse: preserve;\">하이가드 데이베드에 딱 맞게 제작된 </span></p><p><span style=\"white-space-collapse: preserve;\">50cm의 안전한 높이, 도톰한 두께의 범퍼가드는 </span></p><p><span style=\"white-space-collapse: preserve;\">아이가 쉽게 넘어가지 못해요. </span></p><p><span style=\"white-space-collapse: preserve;\">가드들이 서로 지퍼로 연결되어 견고하고,<br>침대 손잡이에 고정해서 흔들리지 않아요.</span><br></p><span style=\"white-space-collapse: preserve;\"><br></span><br><p></p></div>\n<div class=\"img-box\">\n\t<picture data-origin=\"admin-editor-img\">\n\t\t<source media=\"(max-width:767px)\" srcset=\"https://image.hanssem.com/hsimg/gds/Editor/2024/10/07/1728266056301_0.jpg?w=750 2x, https://image.hanssem.com/hsimg/gds/Editor/2024/10/07/1728266056301_0.jpg?w=1125 3x\">\n\t\t<source media=\"(min-width:768px)\" srcset=\"https://image.hanssem.com/hsimg/gds/Editor/2024/10/07/1728266056301_0.jpg?w=870 1x, https://image.hanssem.com/hsimg/gds/Editor/2024/10/07/1728266056301_0.jpg?w=1740 2x, https://image.hanssem.com/hsimg/gds/Editor/2024/10/07/1728266056301_0.jpg?w=2610 3x\">\n\t\t<img src=\"https://image.hanssem.com/hsimg/gds/Editor/2024/10/07/1728266056301_0.jpg\" width=\"\" height=\"\">\n\t</picture>\n</div>\n<div class=\"cont-txt\"><h2><span style=\"white-space-collapse: preserve;\">샘키즈의 사랑스러운 컬러를 담은 </span></h2><h2><span style=\"white-space-collapse: preserve;\">투톤 디자인</span><br></h2><p></p><p><span style=\"white-space-collapse: preserve;\">샘키즈의 시그니처 라이트베이지 컬러와 </span></p><p><span style=\"white-space-collapse: preserve;\">화사한 신상컬러 귀여운 옐로우와 </span></p><p><span style=\"white-space-collapse: preserve;\">차분한 블루 포인트가 가미된<br>투톤 디자인으로 취향에 따라 양면 사용할 수 있어요.</span><span style=\"white-space-collapse: preserve;\"><br></span></p><p><span style=\"white-space-collapse: preserve;\"><br></span><br></p></div>\n<div class=\"img-box\">\n\t<picture data-origin=\"admin-editor-img\">\n\t\t<source media=\"(max-width:767px)\" srcset=\"https://image.hanssem.com/hsimg/gds/Editor/2024/10/07/1728266071403_0.jpg?w=750 2x, https://image.hanssem.com/hsimg/gds/Editor/2024/10/07/1728266071403_0.jpg?w=1125 3x\">\n\t\t<source media=\"(min-width:768px)\" srcset=\"https://image.hanssem.com/hsimg/gds/Editor/2024/10/07/1728266071403_0.jpg?w=870 1x, https://image.hanssem.com/hsimg/gds/Editor/2024/10/07/1728266071403_0.jpg?w=1740 2x, https://image.hanssem.com/hsimg/gds/Editor/2024/10/07/1728266071403_0.jpg?w=2610 3x\">\n\t\t<img src=\"https://image.hanssem.com/hsimg/gds/Editor/2024/10/07/1728266071403_0.jpg\" width=\"\" height=\"\">\n\t</picture>\n</div>\n<div class=\"cont-txt\"><h2><span style=\"white-space-collapse: preserve;\">사랑스러운 리본 포인트</span></h2><p></p><p><span style=\"white-space-collapse: preserve;\">침대 손잡이에 리본으로 묶으면 사랑스러운<br>디자인 포인트를 줄 수 있어요.<br>범퍼가드 고정과 동시에, </span></p><p><span style=\"white-space-collapse: preserve;\">감성적인 아이방을 연출해 보세요.</span><br></p><p><span style=\"white-space-collapse: preserve;\"><br></span><br></p></div>\n<div class=\"img-box\">\n\t<picture data-origin=\"admin-editor-img\">\n\t\t<source media=\"(max-width:767px)\" srcset=\"https://image.hanssem.com/hsimg/gds/Editor/2024/10/07/1728266095735_0.jpg?w=750 2x, https://image.hanssem.com/hsimg/gds/Editor/2024/10/07/1728266095735_0.jpg?w=1125 3x\">\n\t\t<source media=\"(min-width:768px)\" srcset=\"https://image.hanssem.com/hsimg/gds/Editor/2024/10/07/1728266095735_0.jpg?w=870 1x, https://image.hanssem.com/hsimg/gds/Editor/2024/10/07/1728266095735_0.jpg?w=1740 2x, https://image.hanssem.com/hsimg/gds/Editor/2024/10/07/1728266095735_0.jpg?w=2610 3x\">\n\t\t<img src=\"https://image.hanssem.com/hsimg/gds/Editor/2024/10/07/1728266095735_0.jpg\" width=\"\" height=\"\">\n\t</picture>\n</div>\n<div class=\"cont-txt\"><h2><span style=\"white-space-collapse: preserve;\">지퍼 연결형으로 간편한 조립, 분리</span><br></h2><p></p><p><span style=\"white-space-collapse: preserve;\">범퍼가드끼리 지퍼로 연결해 틈새 없이 안전해요.<br>지퍼 손잡이를 아래로 내리면 지퍼가 고정이 되어<br>흘러내리지 않아요.</span></p><p><span style=\"white-space-collapse: preserve;\"><br></span></p><h6><span style=\"white-space-collapse: preserve;\">* 지퍼는 아래에서 위로 연결해주세요.</span></h6><p></p><p><span style=\"white-space-collapse: preserve;\"><br></span></p><p><br></p></div>\n<div class=\"img-box\">\n\t<picture data-origin=\"admin-editor-img\">\n\t\t<source media=\"(max-width:767px)\" srcset=\"https://image.hanssem.com/hsimg/gds/Editor/2024/10/07/1728266119033_0.jpg?w=750 2x, https://image.hanssem.com/hsimg/gds/Editor/2024/10/07/1728266119033_0.jpg?w=1125 3x\">\n\t\t<source media=\"(min-width:768px)\" srcset=\"https://image.hanssem.com/hsimg/gds/Editor/2024/10/07/1728266119033_0.jpg?w=870 1x, https://image.hanssem.com/hsimg/gds/Editor/2024/10/07/1728266119033_0.jpg?w=1740 2x, https://image.hanssem.com/hsimg/gds/Editor/2024/10/07/1728266119033_0.jpg?w=2610 3x\">\n\t\t<img src=\"https://image.hanssem.com/hsimg/gds/Editor/2024/10/07/1728266119033_0.jpg\" width=\"\" height=\"\">\n\t</picture>\n</div>\n<div class=\"cont-txt\"><h2><span style=\"white-space-collapse: preserve;\">손쉽게 커버를 분리 세탁</span><br></h2><p></p><p><span style=\"white-space-collapse: preserve;\">아이 피부에 닿는 거니까 얼룩과 보이지 않는 먼지,<br>세균들이 걱정된다면 커버를 세탁하여 더욱 위생적이고<br>안전하게 사용하세요.</span><span style=\"white-space-collapse: preserve;\"><br></span></p><p><span style=\"white-space-collapse: preserve;\"><br></span><br></p></div>\n<div class=\"img-box\">\n\t<picture data-origin=\"admin-editor-img\">\n\t\t<source media=\"(max-width:767px)\" srcset=\"https://image.hanssem.com/hsimg/gds/Editor/2025/08/07/1754543226590_0.jpg?w=750 2x, https://image.hanssem.com/hsimg/gds/Editor/2025/08/07/1754543226590_0.jpg?w=1125 3x\">\n\t\t<source media=\"(min-width:768px)\" srcset=\"https://image.hanssem.com/hsimg/gds/Editor/2025/08/07/1754543226590_0.jpg?w=870 1x, https://image.hanssem.com/hsimg/gds/Editor/2025/08/07/1754543226590_0.jpg?w=1740 2x, https://image.hanssem.com/hsimg/gds/Editor/2025/08/07/1754543226590_0.jpg?w=2610 3x\">\n\t\t<img src=\"https://image.hanssem.com/hsimg/gds/Editor/2025/08/07/1754543226590_0.jpg\" width=\"\" height=\"\">\n\t</picture>\n</div>\n",
  "cssLinks": [
    "https://res.remodeling.hanssem.com/font/pretendard/pretendard.css",
    "https://store.hanssem.com/_next/static/css/cd8d11070aab510c.css",
    "https://use.fontawesome.com/7f85a56ba4.css",
    "https://fonts.googleapis.com/css2?family=Roboto&display=swap"
  ],
  "viewport": "1920x1080 (Desktop)",
  "scrapedAt": "2025-10-17T08:06:09.605Z"
}